Executions.py
bigQuery_helper.py
cloudFunction_helper.py
gcp_helper.py
pubsub_helper.py
wiraconcha-0.0.14.dist-info/LICENSE.txt
wiraconcha-0.0.14.dist-info/METADATA
wiraconcha-0.0.14.dist-info/WHEEL
wiraconcha-0.0.14.dist-info/top_level.txt
wiraconcha-0.0.14.dist-info/RECORD
